nadc_datahub/__init__.py
nadc_datahub/dataset.py
nadc_datahub/ep_tdic.py
nadc_datahub/image_cutout.py
nadc_datahub-0.2.9.dist-info/METADATA
nadc_datahub-0.2.9.dist-info/WHEEL
nadc_datahub-0.2.9.dist-info/RECORD
