Metadata-Version: 2.1
Name: nadc-datahub
Version: 0.2.9
Summary: A Python package for accessing datasets from NADC DataHub
License: MIT
Keywords: astronomy,data,nadc,datahub
Author: zhangzhen
Author-email: zhangzhen@nao.cas.cn
Requires-Python: >=3.8
Classifier: License :: OSI Approved :: MIT License
Classifier: Programming Language :: Python :: 3
Classifier: Programming Language :: Python :: 3.8
Classifier: Programming Language :: Python :: 3.9
Classifier: Programming Language :: Python :: 3.10
Classifier: Programming Language :: Python :: 3.11
Classifier: Programming Language :: Python :: 3.12
Requires-Dist: csdb (==1.1.0)
Requires-Dist: dotenv (>=0.9.9,<0.10.0)
